ctxzz/__init__.py
ctxzz/__main__.py
ctxzz-1.0.0.dist-info/METADATA
ctxzz-1.0.0.dist-info/WHEEL
ctxzz-1.0.0.dist-info/entry_points.txt
ctxzz-1.0.0.dist-info/licenses/LICENSE
ctxzz-1.0.0.dist-info/RECORD
