Metadata-Version: 2.4
Name: ctxzz
Version: 1.0.0
Summary: Atsushi Omata / ctxzz's animated profile card generator
Project-URL: Homepage, https://omata.me
Project-URL: Repository, https://github.com/ctxzz/ctxzz-profile-card
Project-URL: Issues, https://github.com/ctxzz/ctxzz-profile-card/issues
Author-email: Atsushi Omata <omata.atushi.open@gmail.com>
License: MIT
License-File: LICENSE
Keywords: animation,card,cli,profile,terminal
Classifier: Development Status :: 5 - Production/Stable
Classifier: Environment :: Console
Classifier: Intended Audience :: Developers
Classifier: License :: OSI Approved :: MIT License
Classifier: Operating System :: OS Independent
Classifier: Programming Language :: Python :: 3
Classifier: Programming Language :: Python :: 3.8
Classifier: Programming Language :: Python :: 3.9
Classifier: Programming Language :: Python :: 3.10
Classifier: Programming Language :: Python :: 3.11
Classifier: Programming Language :: Python :: 3.12
Classifier: Topic :: Terminals
Classifier: Topic :: Utilities
Requires-Python: >=3.8
Requires-Dist: terminaltexteffects>=0.10.0
